KSchoolMeal/__init__.py
KSchoolMeal/exceptions.py
KSchoolMeal/getSchoolCode.py
KSchoolMeal/getSchoolMeal.py
KSchoolMeal/models.py
KSchoolMeal/sync.py
k_SchoolMeal-1.1.1a0.dist-info/LICENSE
k_SchoolMeal-1.1.1a0.dist-info/METADATA
k_SchoolMeal-1.1.1a0.dist-info/WHEEL
k_SchoolMeal-1.1.1a0.dist-info/top_level.txt
k_SchoolMeal-1.1.1a0.dist-info/RECORD
