Metadata-Version: 2.1
Name: k-SchoolMeal
Version: 1.1.1.Alpha
Summary: school meal data
Home-page: https://github.com/EGGnmad/K-SchoolMeal
Author: EGGnmad
Author-email: viewnono1219@gmail.com
License: UNKNOWN
Download-URL: https://github.com/EGGnmad/K-SchoolMeal
Keywords: korea,school meal
Platform: UNKNOWN
Requires-Python: >=3.7
License-File: LICENSE
Requires-Dist: aiohttp
